constantdict/__init__.py
constantdict/py.typed
constantdict-2025.2.dist-info/METADATA
constantdict-2025.2.dist-info/WHEEL
constantdict-2025.2.dist-info/licenses/LICENSE
constantdict-2025.2.dist-info/RECORD
