Metadata-Version: 2.4
Name: constantdict
Version: 2025.2
Summary: An immutable dict class.
Project-URL: Homepage, https://github.com/matthiasdiener/constantdict
Project-URL: Documentation, https://matthiasdiener.github.io/constantdict
Project-URL: Issues, https://github.com/matthiasdiener/constantdict/issues
Author-email: Matthias Diener <matthias.diener@gmail.com>
License: MIT License
License-File: LICENSE
Classifier: License :: OSI Approved :: MIT License
Classifier: Operating System :: OS Independent
Classifier: Programming Language :: Python :: 3
Classifier: Topic :: Software Development :: Libraries
Requires-Python: >=3.7
Requires-Dist: importlib-metadata; python_version < '3.8'
Requires-Dist: typing-extensions; python_version < '3.8'
